pi7gurmukhi/__init__.py
pi7gurmukhi/chars.py
pi7gurmukhi-0.1.3.dist-info/LICENSE
pi7gurmukhi-0.1.3.dist-info/METADATA
pi7gurmukhi-0.1.3.dist-info/WHEEL
pi7gurmukhi-0.1.3.dist-info/top_level.txt
pi7gurmukhi-0.1.3.dist-info/RECORD
