Metadata-Version: 2.1
Name: pi7gurmukhi
Version: 0.1.3
Summary: Helpful In Write Correct Punjabi/Gurmukhi On Images, Pdf, Kivy & Others.
Home-page: https://github.com/shivjeetbhullar/gurmukhi
Author: Shivjeet Singh Bhullar
Author-email: bhullarshivjeet@gmail.com
License: UNKNOWN
Platform: UNKNOWN
Classifier: Programming Language :: Python :: 3
Classifier: License :: OSI Approved :: GNU General Public License v3 or later (GPLv3+)
Classifier: Operating System :: OS Independent
Classifier: Natural Language :: Panjabi
Classifier: Programming Language :: Python
Classifier: Topic :: Text Processing :: Fonts
Requires-Python: >=3
